LICENSE
MANIFEST.in
readme.md
setup.py
terminalmdb.py
terminalmdb.egg-info/PKG-INFO
terminalmdb.egg-info/SOURCES.txt
terminalmdb.egg-info/dependency_links.txt
terminalmdb.egg-info/entry_points.txt
terminalmdb.egg-info/top_level.txt