Metadata-Version: 1.0
Name: terminalmdb
Version: 0.0.2
Summary: CLI for IMDB
Home-page: https://github.com/zacoppotamus/TerminaIMdB
Author: Zac Ioannidis
Author-email: me@izac.us
License:     TerminalMDB - CLI for IMDB
